ben_memre/__init__.py
ben_memre/functions.py
ben_memre-0.1.4.dist-info/licenses/LICENSE
ben_memre-0.1.4.dist-info/METADATA
ben_memre-0.1.4.dist-info/WHEEL
ben_memre-0.1.4.dist-info/top_level.txt
ben_memre-0.1.4.dist-info/RECORD
