Metadata-Version: 2.4
Name: ben-memre
Version: 0.1.4
Summary: A special library by Emre with a few functions for AI projects.
Author-email: Memre Ozkan <muh.emreozkan@gmail.com>
Classifier: Programming Language :: Python :: 3
Classifier: License :: OSI Approved :: MIT License
Classifier: Operating System :: OS Independent
Requires-Python: >=3.7
License-File: LICENSE
Requires-Dist: numpy>=1.20.0
Dynamic: license-file
